trionesDevice/__init__.py
trionesdevice-1.0.0.dist-info/METADATA
trionesdevice-1.0.0.dist-info/WHEEL
trionesdevice-1.0.0.dist-info/licenses/LICENSE
trionesdevice-1.0.0.dist-info/RECORD
