Metadata-Version: 2.1
Name: trionesDevice
Version: 1.0.0
Summary: Crossplatform version of trionesControl module
Project-URL: Homepage, https://github.com/DmitriyBukreev/trionesDevice
Project-URL: Bug Tracker, https://github.com/DmitriyBukreev/trionesDevice/issues
Author-email: Bukreev Dmitriy <dmitriy.bukreev.job@gmail.com>
License-File: LICENSE
Classifier: License :: OSI Approved :: MIT License
Classifier: Operating System :: Android
Classifier: Operating System :: MacOS :: MacOS X
Classifier: Operating System :: Microsoft :: Windows :: Windows 10
Classifier: Operating System :: OS Independent
Classifier: Operating System :: POSIX :: Linux
Classifier: Programming Language :: Python :: 3
Requires-Python: >=3.7
Requires-Dist: bleak==0.20.2
